gypp
