Metadata-Version: 1.1
Name: gypp
Version: 1.1.1
Summary: Read GPG encrypted YAML files
Home-page: https://github.com/datadavev/gypp.git
Author: Dave Vieglais
Author-email: datadavev@users.noreply.github.com
License: Apache 2.0
Keywords: gpg,decrypt,yaml,passwords
Platform: UNKNOWN
Classifier: Development Status :: 4 - Beta
Classifier: Environment :: Console
Classifier: Intended Audience :: Developers
Classifier: Topic :: Scientific/Engineering
Classifier: License :: OSI Approved :: Apache Software License
Classifier: Programming Language :: Python :: 3
Classifier: Programming Language :: Python :: 3.5
